{
  "type": "Prerender",
  "expiration": false,
  "isDynamicRoute": false,
  "htmlSize": 8101,
  "group": 15,
  "bypassToken": "a65bd1a173a1a97043db268f8a0ef48c",
  "experimentalBypassFor": [
    {
      "type": "header",
      "key": "Next-Action"
    },
    {
      "type": "header",
      "key": "content-type",
      "value": "multipart/form-data;.*"
    }
  ],
  "fallback": {
    "type": "FileFsRef",
    "mode": 33188,
    "fsPath": "stories.prerender-fallback.html"
  },
  "initialHeaders": {
    "x-nextjs-stale-time": "4294967294",
    "x-nextjs-prerender": "1",
    "x-next-cache-tags": "_N_T_/layout,_N_T_/(marketing)/layout,_N_T_/(marketing)/stories/layout,_N_T_/(marketing)/stories/page,_N_T_/stories",
    "vary": "RSC, Next-Router-State-Tree, Next-Router-Prefetch, Next-Router-Segment-Prefetch"
  },
  "allowQuery": [],
  "allowHeader": [
    "x-matched-path",
    "x-prerender-revalidate",
    "x-prerender-revalidate-if-generated",
    "x-next-revalidated-tags",
    "x-next-revalidate-tag-token"
  ]
}
